waitz_s3_api/__init__.py
waitz_s3_api-0.0.6.dist-info/METADATA
waitz_s3_api-0.0.6.dist-info/RECORD
waitz_s3_api-0.0.6.dist-info/WHEEL
waitz_s3_api-0.0.6.dist-info/top_level.txt
